sca_core/__init__.py
sca_core/config.py
sca_core/log.py
sca_core/mq.py
sca_core/multi_process.py
sca_core/utils.py
sca_core-0.0.6.dist-info/METADATA
sca_core-0.0.6.dist-info/WHEEL
sca_core-0.0.6.dist-info/top_level.txt
sca_core-0.0.6.dist-info/RECORD
